Metadata-Version: 2.4
Name: pyinfra
Version: 3.6
Summary: pyinfra automates/provisions/manages/deploys infrastructure.
Project-URL: homepage, https://pyinfra.com
Project-URL: documentation, https://docs.pyinfra.com
Project-URL: repository, https://github.com/pyinfra-dev/pyinfra
Author-email: Nick / Fizzadar <pointlessrambler@gmail.com>
License-Expression: MIT
License-File: LICENSE.md
Classifier: Development Status :: 5 - Production/Stable
Classifier: Environment :: Console
Classifier: Intended Audience :: Developers
Classifier: Intended Audience :: Information Technology
Classifier: Intended Audience :: System Administrators
Classifier: Operating System :: OS Independent
Classifier: Programming Language :: Python :: 3
Classifier: Programming Language :: Python :: 3.10
Classifier: Programming Language :: Python :: 3.11
Classifier: Programming Language :: Python :: 3.12
Classifier: Programming Language :: Python :: 3.13
Classifier: Topic :: System :: Installation/Setup
Classifier: Topic :: System :: Systems Administration
Classifier: Topic :: Utilities
Requires-Python: <4.0,>=3.10
Requires-Dist: click>2
Requires-Dist: distro<2,>=1.6
Requires-Dist: gevent>=1.5
Requires-Dist: jinja2<4,>3
Requires-Dist: packaging>=16.1
Requires-Dist: paramiko<4,>=2.7
Requires-Dist: pydantic<3,>=2.11
Requires-Dist: python-dateutil<3,>2
Requires-Dist: typeguard<5,>=4
Requires-Dist: typing-extensions; python_version < '3.11'
